eyeware/__init__.py
eyeware/beam_eye_tracker.cp37-win_amd64.pyd
beam_eye_tracker-2.1.0.dist-info/LICENSE.md
beam_eye_tracker-2.1.0.dist-info/METADATA
beam_eye_tracker-2.1.0.dist-info/WHEEL
beam_eye_tracker-2.1.0.dist-info/top_level.txt
beam_eye_tracker-2.1.0.dist-info/RECORD
