Metadata-Version: 2.1
Name: beam-eye-tracker
Version: 2.1.0
Summary: Beam Eye Tracker API - Access real-time head and eye tracking data to build diverse games and applications.
Author-email: Kenneth Funes <kenneth@eyeware.tech>
Maintainer-email: Kenneth Funes <kenneth@eyeware.tech>
License: # Eyeware – Beam SDK Licensing Terms [ BET-SDK-License-1.0 ]
Project-URL: Homepage, https://docs.beam.eyeware.tech/
Project-URL: Documentation, https://docs.beam.eyeware.tech/
Project-URL: Discord, http://bit.ly/4089mMT
Project-URL: Get Beam, https://beam.eyeware.tech/get-beam/
Keywords: eye tracking,head tracking,game development,application
Classifier: Development Status :: 5 - Production/Stable
Classifier: Intended Audience :: Developers
Classifier: Intended Audience :: Education
Classifier: Intended Audience :: Science/Research
Classifier: Operating System :: Microsoft :: Windows
Classifier: License :: Other/Proprietary License
Classifier: Programming Language :: Python :: 3
Classifier: Programming Language :: Python :: 3.7
Classifier: Programming Language :: Python :: 3.8
Classifier: Programming Language :: Python :: 3.9
Classifier: Programming Language :: Python :: 3.10
Classifier: Programming Language :: Python :: 3.11
Classifier: Programming Language :: Python :: 3.12
Classifier: Programming Language :: Python :: 3 :: Only
Requires-Python: >=3.7
License-File: LICENSE.md
Requires-Dist: numpy >=1.5
